cyberdrop_dl/__init__.py
cyberdrop_dl/clients/__init__.py
cyberdrop_dl/clients/download_client.py
cyberdrop_dl/clients/flaresolverr.py
cyberdrop_dl/clients/hash_client.py
cyberdrop_dl/clients/response.py
cyberdrop_dl/clients/scraper_client.py
cyberdrop_dl/compat.py
cyberdrop_dl/config/__init__.py
cyberdrop_dl/config/_common.py
cyberdrop_dl/config/auth_model.py
cyberdrop_dl/config/config_model.py
cyberdrop_dl/config/global_model.py
cyberdrop_dl/constants.py
cyberdrop_dl/crawlers/__init__.py
cyberdrop_dl/crawlers/_chevereto.py
cyberdrop_dl/crawlers/_chibisafe.py
cyberdrop_dl/crawlers/_fluid_player.py
cyberdrop_dl/crawlers/_forum.py
cyberdrop_dl/crawlers/_kvs.py
cyberdrop_dl/crawlers/_one_manager.py
cyberdrop_dl/crawlers/_tubecorporate.py
cyberdrop_dl/crawlers/_yetishare.py
cyberdrop_dl/crawlers/anontransfer.py
cyberdrop_dl/crawlers/anysex.py
cyberdrop_dl/crawlers/archivebate.py
cyberdrop_dl/crawlers/ashemaletube.py
cyberdrop_dl/crawlers/bandcamp.py
cyberdrop_dl/crawlers/beeg.py
cyberdrop_dl/crawlers/box_dot_com.py
cyberdrop_dl/crawlers/bunkrr.py
cyberdrop_dl/crawlers/bunkrr_albums_io.py
cyberdrop_dl/crawlers/buzzheavier.py
cyberdrop_dl/crawlers/camwhores_dot_tv.py
cyberdrop_dl/crawlers/catbox.py
cyberdrop_dl/crawlers/cloudflare_stream.py
cyberdrop_dl/crawlers/coomer.py
cyberdrop_dl/crawlers/crawler.py
cyberdrop_dl/crawlers/cyberdrop.py
cyberdrop_dl/crawlers/cyberfile.py
cyberdrop_dl/crawlers/desivideo.py
cyberdrop_dl/crawlers/dirtyship.py
cyberdrop_dl/crawlers/discourse/__init__.py
cyberdrop_dl/crawlers/discourse/_discourse.py
cyberdrop_dl/crawlers/discourse/models.py
cyberdrop_dl/crawlers/doodstream.py
cyberdrop_dl/crawlers/dropbox.py
cyberdrop_dl/crawlers/e621.py
cyberdrop_dl/crawlers/efukt.py
cyberdrop_dl/crawlers/ehentai.py
cyberdrop_dl/crawlers/eightmuses.py
cyberdrop_dl/crawlers/eporner.py
cyberdrop_dl/crawlers/erome.py
cyberdrop_dl/crawlers/fapello.py
cyberdrop_dl/crawlers/fileditch.py
cyberdrop_dl/crawlers/files_vc.py
cyberdrop_dl/crawlers/flugel_anime.py
cyberdrop_dl_patched-8.10.0.dist-info/METADATA
cyberdrop_dl_patched-8.10.0.dist-info/WHEEL
cyberdrop_dl_patched-8.10.0.dist-info/entry_points.txt
cyberdrop_dl_patched-8.10.0.dist-info/licenses/LICENSE
cyberdrop_dl_patched-8.10.0.dist-info/RECORD
