Metadata-Version: 2.4
Name: cyberdrop-dl-patched
Version: 8.10.0
Summary: Bulk downloader for multiple file hosts
License-Expression: GPL-3.0-only
License-File: LICENSE
Author: Jacob B
Author-email: admin@script-ware.net
Requires-Python: >=3.11,<4
Classifier: Programming Language :: Python :: 3
Classifier: Programming Language :: Python :: 3.11
Classifier: Programming Language :: Python :: 3.12
Classifier: Programming Language :: Python :: 3.13
Classifier: Programming Language :: Python :: 3.14
Requires-Dist: aiodns (>=4.0.0)
Requires-Dist: aiofiles (>=25.1.0)
Requires-Dist: aiohttp[speedups] (>=3.13.3)
Requires-Dist: aiolimiter (>=1.2.1)
Requires-Dist: aiosqlite (==0.17.0)
Requires-Dist: apprise (>=1.9.6)
Requires-Dist: asyncpraw (>=7.8.1)
Requires-Dist: beautifulsoup4 (>=4.14.3)
Requires-Dist: certifi (>=2026.1.4)
Requires-Dist: curl-cffi (>=0.13,<0.14) ; implementation_name == "cpython"
Requires-Dist: dateparser (>=1.2.2)
Requires-Dist: get-video-properties (>=0.1.1)
Requires-Dist: imagesize (>=1.4.1)
Requires-Dist: inquirerpy (>=0.3.4)
Requires-Dist: jeepney (>=0.9.0) ; "bsd" in sys_platform or sys_platform == "linux"
Requires-Dist: m3u8 (>=6.0.0)
Requires-Dist: myjdapi (>=1.1.10)
Requires-Dist: packaging (>=25.0)
Requires-Dist: propcache (>=0.4.1)
Requires-Dist: psutil (>=7.2.1)
Requires-Dist: pycares (>=4.10.0)
Requires-Dist: pycryptodome (>=3.23.0)
Requires-Dist: pydantic (>=2.12.4)
Requires-Dist: pyyaml (>=6.0.3)
Requires-Dist: rich (>=14.2.0)
Requires-Dist: send2trash (>=2.0.0)
Requires-Dist: truststore (>=0.10.4)
Requires-Dist: xxhash (>=3.6.0)
Requires-Dist: yarl (>=1.22.0)
Project-URL: Changelog, https://github.com/jbsparrow/CyberDropDownloader/blob/master/CHANGELOG.md
Project-URL: Documentation, https://script-ware.gitbook.io/cyberdrop-dl/
Project-URL: Repository, https://github.com/jbsparrow/CyberDropDownloader
